{
  "date_raw": "2026/07/24",
  "date_label": "2026年7月24日(金)",
  "unit": "円/kWh",
  "slots": 48,
  "areas": {
    "北海道": [
      11.5,
      11.41,
      9.9,
      9.71,
      11.5,
      11.5,
      9.91,
      9.91,
      9.91,
      9.62,
      9.62,
      9.62,
      11.5,
      10.03,
      11.5,
      9.91,
      9.62,
      9.62,
      9.62,
      9.91,
      8.78,
      9.91,
      11.5,
      10.45,
      9.91,
      9.91,
      14.47,
      14.51,
      12.0,
      13.35,
      14.21,
      14.31,
      17.0,
      17.0,
      17.0,
      17.0,
      12.0,
      28.0,
      26.99,
      24.83,
      15.26,
      19.33,
      12.0,
      11.5,
      12.0,
      11.5,
      9.62,
      9.91
    ],
    "東北": [
      21.97,
      18.97,
      18.7,
      18.05,
      17.81,
      16.66,
      17.24,
      17.0,
      17.24,
      17.24,
      16.35,
      16.56,
      17.38,
      18.02,
      18.78,
      18.8,
      21.08,
      28.34,
      25.0,
      25.99,
      22.5,
      20.91,
      21.0,
      21.5,
      18.81,
      18.78,
      21.0,
      26.99,
      28.04,
      26.55,
      25.0,
      27.0,
      32.5,
      32.5,
      27.5,
      29.69,
      30.0,
      28.0,
      26.99,
      24.83,
      19.19,
      19.33,
      18.37,
      21.09,
      20.0,
      18.66,
      20.0,
      17.99
    ],
    "東京": [
      21.97,
      18.97,
      18.7,
      18.05,
      17.81,
      16.66,
      17.24,
      17.0,
      17.24,
      17.24,
      16.35,
      16.56,
      17.38,
      18.02,
      18.78,
      18.8,
      21.08,
      28.34,
      25.0,
      25.99,
      22.5,
      20.91,
      21.0,
      21.5,
      18.81,
      18.78,
      21.0,
      26.99,
      28.04,
      29.1,
      26.99,
      33.5,
      45.0,
      45.31,
      33.0,
      29.69,
      30.0,
      28.0,
      26.99,
      24.83,
      19.19,
      19.33,
      18.37,
      21.09,
      20.0,
      18.66,
      20.0,
      17.99
    ],
    "中部": [
      19.01,
      18.19,
      16.72,
      15.93,
      15.0,
      15.39,
      15.0,
      14.96,
      15.52,
      16.35,
      16.35,
      15.99,
      15.92,
      15.39,
      15.52,
      17.06,
      19.64,
      20.2,
      19.86,
      20.03,
      20.21,
      20.2,
      20.2,
      20.2,
      18.0,
      18.59,
      21.0,
      26.99,
      28.04,
      29.1,
      29.02,
      35.0,
      45.0,
      45.31,
      45.32,
      45.29,
      45.29,
      45.29,
      45.1,
      45.09,
      31.89,
      31.49,
      31.48,
      27.5,
      24.51,
      18.66,
      20.0,
      17.99
    ],
    "北陸": [
      19.01,
      18.19,
      16.72,
      15.93,
      15.0,
      15.39,
      15.0,
      14.96,
      15.52,
      16.35,
      16.35,
      15.99,
      15.92,
      15.39,
      15.52,
      17.06,
      19.64,
      20.2,
      19.86,
      20.03,
      20.21,
      20.2,
      20.2,
      20.2,
      18.0,
      18.59,
      21.0,
      26.99,
      28.04,
      29.1,
      29.02,
      35.0,
      45.0,
      45.31,
      45.32,
      45.29,
      45.29,
      45.29,
      45.1,
      45.09,
      31.89,
      31.49,
      31.48,
      27.5,
      24.51,
      18.66,
      20.0,
      17.99
    ],
    "関西": [
      19.01,
      18.19,
      16.72,
      15.93,
      15.0,
      15.39,
      15.0,
      14.96,
      15.52,
      16.35,
      16.35,
      15.99,
      15.92,
      15.39,
      15.52,
      17.06,
      19.64,
      20.2,
      19.86,
      20.03,
      20.21,
      20.2,
      20.2,
      20.2,
      18.0,
      18.59,
      21.0,
      26.99,
      28.04,
      29.1,
      29.02,
      35.0,
      45.0,
      45.31,
      45.32,
      50.0,
      50.01,
      58.38,
      50.01,
      45.09,
      31.89,
      31.49,
      31.48,
      27.5,
      24.51,
      18.66,
      20.0,
      17.99
    ],
    "中国": [
      19.01,
      18.19,
      16.72,
      15.93,
      15.0,
      15.39,
      15.0,
      14.96,
      15.52,
      16.35,
      16.35,
      15.99,
      15.92,
      15.39,
      15.52,
      17.06,
      19.64,
      20.2,
      19.86,
      20.03,
      20.21,
      20.2,
      20.2,
      20.2,
      17.69,
      17.11,
      17.11,
      12.71,
      12.92,
      17.09,
      17.67,
      35.0,
      45.0,
      45.31,
      45.32,
      50.0,
      50.01,
      58.38,
      50.01,
      45.09,
      31.89,
      31.49,
      31.48,
      27.5,
      24.51,
      18.66,
      20.0,
      17.99
    ],
    "四国": [
      19.01,
      18.19,
      16.72,
      15.93,
      15.0,
      15.39,
      15.0,
      14.96,
      15.52,
      16.35,
      16.35,
      15.99,
      15.92,
      15.39,
      15.52,
      17.06,
      19.64,
      20.2,
      19.86,
      7.97,
      7.91,
      7.8,
      7.27,
      7.27,
      7.18,
      7.03,
      7.14,
      7.25,
      7.32,
      8.1,
      14.0,
      35.0,
      45.0,
      45.31,
      45.32,
      50.0,
      50.01,
      58.38,
      50.01,
      45.09,
      31.89,
      31.49,
      31.48,
      27.5,
      24.51,
      18.66,
      20.0,
      17.99
    ],
    "九州": [
      19.01,
      18.19,
      16.72,
      15.93,
      15.0,
      15.39,
      15.0,
      14.96,
      15.52,
      16.35,
      16.35,
      15.99,
      15.92,
      14.16,
      12.01,
      10.69,
      14.16,
      14.16,
      14.16,
      14.16,
      10.69,
      10.69,
      10.69,
      10.69,
      10.14,
      10.14,
      10.69,
      10.69,
      12.92,
      14.16,
      17.67,
      35.0,
      45.0,
      45.31,
      45.32,
      50.0,
      50.01,
      58.38,
      50.01,
      45.09,
      31.89,
      31.49,
      31.48,
      27.5,
      24.51,
      18.66,
      20.0,
      17.99
    ]
  }
}